cuecloud
