Metadata-Version: 1.1
Name: cuecloud
Version: 1.0.3
Summary: Integration library for CueCloud
Home-page: https://github.com/cuecloud/cuecloud-py
Author: Cuecloud
Author-email: info@cuecloud.com
License: MIT License
Platform: any
Classifier: Development Status :: 4 - Beta
Classifier: Intended Audience :: Developers
Classifier: License :: OSI Approved :: MIT License
Classifier: Operating System :: OS Independent
Classifier: Programming Language :: Python
Classifier: Programming Language :: Python :: 2.6
Classifier: Programming Language :: Python :: 2.7
Classifier: Topic :: Software Development :: Libraries :: Python Modules
